__init__.py
adapter.py
bit_tool.py
const.py
indoor_unit.py
modbus_client.py
proxy.py
register_area.py
pydta116a621/__init__.py
pydta116a621/adapter.py
pydta116a621/bit_tool.py
pydta116a621/const.py
pydta116a621/indoor_unit.py
pydta116a621/modbus_client.py
pydta116a621/proxy.py
pydta116a621/register_area.py
pydta116a621-0.3.0.dist-info/METADATA
pydta116a621-0.3.0.dist-info/WHEEL
pydta116a621-0.3.0.dist-info/top_level.txt
pydta116a621-0.3.0.dist-info/RECORD
